{"_type":"export","__export_format":4,"__export_date":"2022-11-06T18:30:11.666Z","__export_source":"insomnia.desktop.app:v2022.4.0","resources":[{"_id":"req_de8f7684d5a648b6b15411dc79148210","parentId":"fld_49fa1e390d4a42208be7bcc3753faf61","modified":1667746324519,"created":1667746324519,"url":"http://localhost:8080/order/63671b0ace78007acf7e1cdb","name":"Deletar Pedido","description":"","method":"DELETE","body":{},"parameters":[],"headers":[],"authentication":{},"metaSortKey":-1667691479413,"isPrivate":false,"settingStoreCookies":true,"settingSendCookies":true,"settingDisableRenderRequestBody":false,"settingEncodeUrl":true,"settingRebuildPath":true,"settingFollowRedirects":"global","_type":"request"},{"_id":"fld_49fa1e390d4a42208be7bcc3753faf61","parentId":"wrk_ab64098478a4434c8270d673f6c7549d","modified":1667746337645,"created":1667746324508,"name":"QUARKUS - ORDERS","description":"","environment":{},"environmentPropertyOrder":null,"metaSortKey":-1000000000,"_type":"request_group"},{"_id":"wrk_ab64098478a4434c8270d673f6c7549d","parentId":null,"modified":1667682230289,"created":1667653273459,"name":"Codeforce","description":"","scope":"collection","_type":"workspace"},{"_id":"req_60ab177adbe54588a18ec744a6cc589d","parentId":"fld_49fa1e390d4a42208be7bcc3753faf61","modified":1667759291458,"created":1667746324516,"url":"http://localhost:8080/order","name":"Criar Pedido","description":"","method":"POST","body":{"mimeType":"application/json","text":"{\n\t\"amount\" : 15.00,\n\t\"clientId\" : \"12151511316\",\n\t\"status\" : \"Enviado para análise\",\n\t\"dateStart\" : \"2022-10-31\",\n\t\"products\" : [\n\t\t{\n\t\t\t\"product\": {\n\t\t\t\t\"id\" : \"11111\",\n\t\t\t\t\"name\" : \"Trakinas\",\n\t\t\t\t\"price\" : 1.60\n\t\t\t}, \n\t\t\t\"amount\": 98\n\t\t}\n\t]\n}"},"parameters":[],"headers":[{"name":"Content-Type","value":"application/json","id":"pair_e38165c719ff43f5bc9496e1dd62040c"}],"authentication":{},"metaSortKey":-1667691479363,"isPrivate":false,"settingStoreCookies":true,"settingSendCookies":true,"settingDisableRenderRequestBody":false,"settingEncodeUrl":true,"settingRebuildPath":true,"settingFollowRedirects":"global","_type":"request"},{"_id":"req_80f647a73a1e4952af351064add4f8a4","parentId":"fld_49fa1e390d4a42208be7bcc3753faf61","modified":1667759310085,"created":1667746324514,"url":"http://localhost:8080/order/","name":"Atualizar Pedido","description":"","method":"PATCH","body":{"mimeType":"application/json","text":"{\n\t\"id\" : \"6367fb452e829d064ee28137\",\n\t\"amount\" : 20.00,\n\t\"idClient\" : \"12151511316\",\n\t\"status\" : \"Enviado para análise\",\n\t\"dateStart\" : \"2022-10-31\",\n\t\"products\" : [\n\t\t{\n\t\t\t\"product\": {\n\t\t\t\t\"id\" : \"11111\",\n\t\t\t\t\"name\" : \"Trakinas\",\n\t\t\t\t\"price\" : 1.60\n\t\t\t}, \n\t\t\t\"amount\": 90\n\t\t}\n\t]\n}"},"parameters":[],"headers":[{"name":"Content-Type","value":"application/json","id":"pair_e38165c719ff43f5bc9496e1dd62040c"}],"authentication":{},"metaSortKey":-1667691479313,"isPrivate":false,"settingStoreCookies":true,"settingSendCookies":true,"settingDisableRenderRequestBody":false,"settingEncodeUrl":true,"settingRebuildPath":true,"settingFollowRedirects":"global","_type":"request"},{"_id":"req_f6f50e70bdcf44d1adc46135471b9ad4","parentId":"fld_49fa1e390d4a42208be7bcc3753faf61","modified":1667746324510,"created":1667746324510,"url":"http://localhost:8080/order","name":"Listar Pedido","description":"","method":"GET","body":{},"parameters":[],"headers":[],"authentication":{},"metaSortKey":-1667691479263,"isPrivate":false,"settingStoreCookies":true,"settingSendCookies":true,"settingDisableRenderRequestBody":false,"settingEncodeUrl":true,"settingRebuildPath":true,"settingFollowRedirects":"global","_type":"request"},{"_id":"req_0bbd2341aeee44ddbd1055678b2caf43","parentId":"fld_49fa1e390d4a42208be7bcc3753faf61","modified":1667759173041,"created":1667746324512,"url":"http://localhost:8080/order/6367fb452e829d064ee28137","name":"Buscar Pedido","description":"","method":"GET","body":{},"parameters":[],"headers":[],"authentication":{},"metaSortKey":-1667691438871,"isPrivate":false,"settingStoreCookies":true,"settingSendCookies":true,"settingDisableRenderRequestBody":false,"settingEncodeUrl":true,"settingRebuildPath":true,"settingFollowRedirects":"global","_type":"request"},{"_id":"env_d8ebc9159ebaecd5514999b103eab04e42eb766a","parentId":"wrk_ab64098478a4434c8270d673f6c7549d","modified":1667653273475,"created":1667653273475,"name":"Base Environment","data":{},"dataPropertyOrder":null,"color":null,"isPrivate":false,"metaSortKey":1667653273475,"_type":"environment"},{"_id":"jar_d8ebc9159ebaecd5514999b103eab04e42eb766a","parentId":"wrk_ab64098478a4434c8270d673f6c7549d","modified":1667653273476,"created":1667653273476,"name":"Default Jar","cookies":[],"_type":"cookie_jar"},{"_id":"spc_277588e4a4fb4581bbde85234baea627","parentId":"wrk_ab64098478a4434c8270d673f6c7549d","modified":1667653273469,"created":1667653273469,"fileName":"Serverless","contents":"","contentType":"yaml","_type":"api_spec"}]}